HuoYan_monitoring/HuoYan_monitoring.py
HuoYan_monitoring/__init__.py
HuoYan_monitoring/dash_app.py
HuoYan_monitoring/utils.py
HuoYan_monitoring-0.1.dist-info/METADATA
HuoYan_monitoring-0.1.dist-info/RECORD
HuoYan_monitoring-0.1.dist-info/WHEEL
HuoYan_monitoring-0.1.dist-info/top_level.txt
